.travis.yml
LICENSE
MANIFEST.in
Makefile
README.md
hello_nngen.py
pytest.ini
setup.py
docker/Dockerfile
docs/Makefile
docs/conf.py
docs/index.rst
docs/operator.rst
docs/pynq.rst
examples/Makefile
examples/cnn/Makefile
examples/cnn/cnn.py
examples/darknet_yolov3_tiny/Makefile
examples/darknet_yolov3_tiny/car416x416.png
examples/darknet_yolov3_tiny/darknet_yolov3_tiny.py
examples/mlp/Makefile
examples/mlp/mlp.py
examples/torchvision_onnx_resnet18/Makefile
examples/torchvision_onnx_resnet18/car.png
examples/torchvision_onnx_resnet18/chair.png
examples/torchvision_onnx_resnet18/imagenet_class_index.json
examples/torchvision_onnx_resnet18/torchvision_onnx_resnet18.py
examples/torchvision_onnx_vgg11/Makefile
examples/torchvision_onnx_vgg11/car.png
examples/torchvision_onnx_vgg11/chair.png
examples/torchvision_onnx_vgg11/imagenet_class_index.json
examples/torchvision_onnx_vgg11/torchvision_onnx_vgg11.py
examples/torchvision_onnx_vgg11/ultra96v2_pynq_onnx_vgg11.ipynb
examples/torchvision_onnx_vgg11/ultra96v2_pynq_onnx_vgg11.py
nngen/Makefile
nngen/VERSION
nngen/__init__.py
nngen/basic_types.py
nngen/dtype_list.py
nngen/eval.py
nngen/scheduler.py
nngen/sim.py
nngen/storage.py
nngen/substreams.py
nngen/util.py
nngen/verilog.py
nngen/version.py
nngen.egg-info/PKG-INFO
nngen.egg-info/SOURCES.txt
nngen.egg-info/dependency_links.txt
nngen.egg-info/requires.txt
nngen.egg-info/top_level.txt
nngen/onnx/__init__.py
nngen/onnx/act_func.py
nngen/onnx/basic.py
nngen/onnx/batchnormalization.py
nngen/onnx/cast.py
nngen/onnx/ceil.py
nngen/onnx/concat.py
nngen/onnx/conv.py
nngen/onnx/exp.py
nngen/onnx/flatten.py
nngen/onnx/floor.py
nngen/onnx/gather.py
nngen/onnx/gemm.py
nngen/onnx/identity.py
nngen/onnx/pad.py
nngen/onnx/pool.py
nngen/onnx/reduce.py
nngen/onnx/reshape.py
nngen/onnx/shape.py
nngen/onnx/slice_.py
nngen/onnx/squeeze.py
nngen/onnx/transpose.py
nngen/onnx/upsample.py
nngen/onnx/util.py
nngen/operator/__init__.py
nngen/operator/basic.py
nngen/operator/binary_weight_conv2d.py
nngen/operator/concat.py
nngen/operator/conv2d.py
nngen/operator/exp.py
nngen/operator/extern.py
nngen/operator/leaky_relu.py
