Metadata-Version: 2.1
Name: nngen
Version: 1.3.4
Summary: A Fully-Customizable Hardware Synthesis Compiler for Deep Neural Network
Home-page: https://github.com/NNgen/nngen
Author: Shinya Takamaeda-Yamazaki
License: Apache License 2.0
Keywords: Neural Network,Deep Learning,FPGA,High-Level Synthesis
Provides-Extra: test
License-File: LICENSE
